descending_orderlibrary/__init__.py
descending_orderlibrary/descending_orderpkg6753.py
descending_order_package-0.0.1.dist-info/METADATA
descending_order_package-0.0.1.dist-info/WHEEL
descending_order_package-0.0.1.dist-info/top_level.txt
descending_order_package-0.0.1.dist-info/RECORD
