Metadata-Version: 2.1
Name: descending-order-package
Version: 0.0.1
Summary: a descending order package
Author: atif rafique
Author-email: <msdsf22m019@pucit.edu.pk>
Keywords: python,video,stream,video stream,camera stream,sockets
Classifier: Development Status :: 1 - Planning
Classifier: Intended Audience :: Developers
Classifier: Programming Language :: Python :: 3
Classifier: Operating System :: Unix
Classifier: Operating System :: MacOS :: MacOS X
Classifier: Operating System :: Microsoft :: Windows
